replayer_adapter_python/__init__.py
replayer_adapter_python/replayer.py
temporal_replayer_adapter_python-1.0.3.dist-info/licenses/LICENSE
temporal_replayer_adapter_python-1.0.3.dist-info/METADATA
temporal_replayer_adapter_python-1.0.3.dist-info/WHEEL
temporal_replayer_adapter_python-1.0.3.dist-info/top_level.txt
temporal_replayer_adapter_python-1.0.3.dist-info/RECORD
