Metadata-Version: 2.4
Name: temporal-replayer-adapter-python
Version: 1.0.3
Summary: Python Replayer Adapter for Temporal workflows with debugging capabilities
Author-email: Duy Phuong Nguyen <knowledge.phuongnguyen@gmail.com>
License-Expression: MIT
Project-URL: Homepage, https://github.com/phuongdnguyen/temporal-workflow-replay-debugger
Project-URL: Repository, https://github.com/phuongdnguyen/temporal-workflow-replay-debugger
Project-URL: Issues, https://github.com/phuongdnguyen/temporal-workflow-replay-debugger/issues
Project-URL: Documentation, https://github.com/phuongdnguyen/temporal-workflow-replay-debugger/blob/main/replayer-adapter-python/README.md
Keywords: temporal,workflow,debugging,replay,interceptor
Classifier: Development Status :: 3 - Alpha
Classifier: Intended Audience :: Developers
Classifier: Programming Language :: Python :: 3
Classifier: Programming Language :: Python :: 3.8
Classifier: Programming Language :: Python :: 3.9
Classifier: Programming Language :: Python :: 3.10
Classifier: Programming Language :: Python :: 3.11
Classifier: Programming Language :: Python :: 3.12
Classifier: Topic :: Software Development :: Debuggers
Classifier: Topic :: Software Development :: Libraries :: Python Modules
Requires-Python: >=3.8
License-File: LICENSE
Requires-Dist: temporalio>=1.15.0
Requires-Dist: requests>=2.32.0
Provides-Extra: dev
Requires-Dist: pytest>=6.0; extra == "dev"
Requires-Dist: pytest-asyncio; extra == "dev"
Requires-Dist: black; extra == "dev"
Requires-Dist: isort; extra == "dev"
Requires-Dist: mypy; extra == "dev"
Dynamic: license-file
